kbp2video/__init__.py
kbp2video/__main__.py
kbp2video/_gui.py
kbp2video/advanced_editor.py
kbp2video/advanced_options.py
kbp2video/progress_window.py
kbp2video/utils.py
kbp2video-0.2.2.dist-info/licenses/LICENSE
kbp2video-0.2.2.dist-info/METADATA
kbp2video-0.2.2.dist-info/WHEEL
kbp2video-0.2.2.dist-info/entry_points.txt
kbp2video-0.2.2.dist-info/top_level.txt
kbp2video-0.2.2.dist-info/RECORD
