Metadata-Version: 2.4
Name: kbp2video
Version: 0.2.2
License-File: LICENSE
Requires-Dist: PySide6-Essentials
Requires-Dist: ffmpeg-python
Requires-Dist: kbputils>=0.2.4
Requires-Dist: lastversion
Dynamic: license-file
